smartmine/__init__.py
smartmine/test/__init__.py
smartmine/test/test_health.py
smartmine/test/test_usage.py
smartmine/utils/__init__.py
smartmine/utils/credentials.py
smartmine/utils/exception.py
smartmine/utils/health.py
smartmine/utils/image.py
smartmine/utils/model.py
smartmine/utils/request.py
smartmine/utils/service.py
smartmine-1.0.3.dist-info/LICENSE
smartmine-1.0.3.dist-info/METADATA
smartmine-1.0.3.dist-info/WHEEL
smartmine-1.0.3.dist-info/top_level.txt
smartmine-1.0.3.dist-info/RECORD
